MANIFEST.in
README.rst
VERSION
setup.cfg
setup.py
wsgiauth0/__init__.py
wsgiauth0/config_dynamodb.py
wsgiauth0/config_yaml.py
wsgiauth0/exception.py
wsgiauth0.egg-info/PKG-INFO
wsgiauth0.egg-info/SOURCES.txt
wsgiauth0.egg-info/dependency_links.txt
wsgiauth0.egg-info/entry_points.txt
wsgiauth0.egg-info/requires.txt
wsgiauth0.egg-info/top_level.txt