Metadata-Version: 1.0
Name: wsgiauth0
Version: 0.0.19
Summary: Auth0 middleware for multiple client configurations
Home-page: https://gitlab.com/dialogue/wsgiauth0
Author: UNKNOWN
Author-email: UNKNOWN
License: MIT
Platform: UNKNOWN
